MANIFEST.in
README.md
setup.py
myria/__init__.py
myria/connection.py
myria/errors.py
myria/extension.py
myria/fluent.py
myria/plans.py
myria/query.py
myria/relation.py
myria/schema.py
myria/udf.py
myria/cmd/__init__.py
myria/cmd/upload_file.py
myria/test/__init__.py
myria/test/mock.py
myria/test/test_cmd.py
myria/test/test_connection.py
myria/test/test_connection_query.py
myria/test/test_extension.py
myria/test/test_fluent.py
myria/test/test_logs.py
myria/test/test_plans.py
myria/test/test_query.py
myria/test/test_relation.py
myria/test/test_schema.py
myria/test/test_style.py
myria/test/test_udf.py
myria/test/test_workers.py
myria/utility/__init__.py
myria/utility/cloudpickle.py
myria_python.egg-info/PKG-INFO
myria_python.egg-info/SOURCES.txt
myria_python.egg-info/dependency_links.txt
myria_python.egg-info/entry_points.txt
myria_python.egg-info/requires.txt
myria_python.egg-info/top_level.txt