Metadata-Version: 1.0
Name: myria-python
Version: 1.3.1
Summary: Python interface for Myria.
Home-page: https://github.com/uwescience/myria
Author: Brandon Haynes, Daniel Halperin
Author-email: bhaynes@cs.washington.edu
License: UNKNOWN
Platform: UNKNOWN
